{
  "complete": true,
  "pdg_name": "chain_7v_6e",
  "pdg_index": 0,
  "replicate": 47,
  "cpd_seed": 47200141,
  "graph": {
    "variables": [
      {
        "name": "A",
        "domain": [
          "a0",
          "a1"
        ]
      },
      {
        "name": "B",
        "domain": [
          "b0",
          "b1",
          "b2"
        ]
      },
      {
        "name": "C",
        "domain": [
          "c0",
          "c1",
          "c2"
        ]
      },
      {
        "name": "D",
        "domain": [
          "d0",
          "d1",
          "d2"
        ]
      },
      {
        "name": "E",
        "domain": [
          "e0",
          "e1"
        ]
      },
      {
        "name": "F",
        "domain": [
          "f0",
          "f1",
          "f2"
        ]
      },
      {
        "name": "G",
        "domain": [
          "g0",
          "g1"
        ]
      }
    ],
    "edges": [
      {
        "label": "p1",
        "src": "A",
        "src_atoms": [
          "A"
        ],
        "tgt": "B",
        "tgt_atoms": [
          "B"
        ],
        "alpha": 1.0,
        "beta": 1.0
      },
      {
        "label": "p2",
        "src": "B",
        "src_atoms": [
          "B"
        ],
        "tgt": "C",
        "tgt_atoms": [
          "C"
        ],
        "alpha": 1.0,
        "beta": 1.0
      },
      {
        "label": "p3",
        "src": "C",
        "src_atoms": [
          "C"
        ],
        "tgt": "D",
        "tgt_atoms": [
          "D"
        ],
        "alpha": 1.0,
        "beta": 1.0
      },
      {
        "label": "p4",
        "src": "E",
        "src_atoms": [
          "E"
        ],
        "tgt": "A",
        "tgt_atoms": [
          "A"
        ],
        "alpha": 1.0,
        "beta": 1.0
      },
      {
        "label": "p5",
        "src": "G",
        "src_atoms": [
          "G"
        ],
        "tgt": "D",
        "tgt_atoms": [
          "D"
        ],
        "alpha": 1.0,
        "beta": 1.0
      },
      {
        "label": "p6",
        "src": "E",
        "src_atoms": [
          "E"
        ],
        "tgt": "C",
        "tgt_atoms": [
          "C"
        ],
        "alpha": 1.0,
        "beta": 1.0
      }
    ]
  },
  "cpds": [
    {
      "label": "p1",
      "src": "A",
      "tgt": "B",
      "shape": [
        2,
        3
      ],
      "values": [
        [
          0.0018371667072910772,
          0.4781997393321305,
          0.5199630939605784
        ],
        [
          0.34406920476470376,
          0.12707157677952732,
          0.5288592184557689
        ]
      ]
    },
    {
      "label": "p2",
      "src": "B",
      "tgt": "C",
      "shape": [
        3,
        3
      ],
      "values": [
        [
          0.4057153617837612,
          0.025755332403906154,
          0.5685293058123326
        ],
        [
          0.41395190410375315,
          0.1045627186617122,
          0.48148537723453466
        ],
        [
          0.3467051696098449,
          0.18587394053621656,
          0.46742088985393854
        ]
      ]
    },
    {
      "label": "p3",
      "src": "C",
      "tgt": "D",
      "shape": [
        3,
        3
      ],
      "values": [
        [
          0.02281674897973771,
          0.7996086994349628,
          0.17757455158529944
        ],
        [
          0.3419093268384638,
          0.32385976379109693,
          0.3342309093704394
        ],
        [
          0.6480662996231603,
          0.15440757273781425,
          0.19752612763902555
        ]
      ]
    },
    {
      "label": "p4",
      "src": "E",
      "tgt": "A",
      "shape": [
        2,
        2
      ],
      "values": [
        [
          0.4781885689662704,
          0.5218114310337296
        ],
        [
          0.5482507312638103,
          0.4517492687361897
        ]
      ]
    },
    {
      "label": "p5",
      "src": "G",
      "tgt": "D",
      "shape": [
        2,
        3
      ],
      "values": [
        [
          0.5318458483632197,
          0.2957346878924355,
          0.17241946374434483
        ],
        [
          0.3669637989119281,
          0.3087024625109156,
          0.3243337385771564
        ]
      ]
    },
    {
      "label": "p6",
      "src": "E",
      "tgt": "C",
      "shape": [
        2,
        3
      ],
      "values": [
        [
          0.16218147697577218,
          0.35959876698994275,
          0.47821975603428507
        ],
        [
          0.48751162270361326,
          0.47135398401871925,
          0.04113439327766749
        ]
      ]
    }
  ],
  "strategy_results": {
    "uniform": {
      "pdg_name": "chain_7v_6e",
      "strategy": "uniform",
      "replicate": 47,
      "initial": 0.1570175439119339,
      "final": 0.0017967077437788248,
      "resolution_pct": 98.85572802948278,
      "distortion_tv": 0.5145087006166853,
      "tv_theta_trace": [
        0.0,
        0.2985812500777561,
        0.5743173394127982,
        0.806703611237718,
        0.9913783643282564,
        1.189919639684572,
        1.3557402748947354,
        1.5077873852303436,
        1.554411237814044,
        1.588294091155121,
        1.6260637625873209,
        1.6651865728424184,
        1.6305538064214187,
        1.6184057423529756,
        1.6314521684117285,
        1.5726293082652698,
        1.67743269020246,
        1.7296270500994826,
        1.7410258156467757,
        1.791510762867657,
        1.8129226444425004
      ],
      "success": true
    },
    "partial": {
      "pdg_name": "chain_7v_6e",
      "strategy": "partial",
      "replicate": 47,
      "initial": 0.1570175439119339,
      "final": 0.024368170648813248,
      "resolution_pct": 84.48060640759955,
      "distortion_tv": 0.410124893240438,
      "tv_theta_trace": [
        0.0,
        0.06407585070989963,
        0.11533425712201045,
        0.2204286924512769,
        0.3475864712021821,
        0.36994531588630214,
        0.402212561807796,
        0.4265885068925123,
        0.4657307075705606,
        0.4814530313435378,
        0.5695169122737017,
        0.6555629874369444,
        0.6925060589390748,
        0.6879938276479127,
        0.7804370465844247,
        0.7799780187354782,
        0.8104766736543935,
        0.8544972122088138,
        0.8890861658089133,
        0.9013091858471162,
        0.8702081881995622
      ],
      "success": true
    },
    "hub": {
      "pdg_name": "chain_7v_6e",
      "strategy": "hub",
      "replicate": 47,
      "initial": 0.1570175439119339,
      "final": 0.008038565516471863,
      "resolution_pct": 94.88046665601874,
      "distortion_tv": 0.39732264472526435,
      "tv_theta_trace": [
        0.0,
        0.257042217483789,
        0.5032997574906312,
        0.6884377516420812,
        0.8668766123834504,
        0.9974539810360438,
        1.1144649857884632,
        1.2177029662294,
        1.1544053934653125,
        1.1318099217632498,
        1.1281239696742258,
        1.18385784457669,
        1.1433490956352288,
        1.2258289577526327,
        1.2326823114732584,
        1.308165241234653,
        1.3680419286806735,
        1.3681563067669003,
        1.4700684848530083,
        1.5119415520885982,
        1.4962509994232276
      ],
      "success": true
    }
  }
}