{
  "complete": true,
  "pdg_name": "chain_5v_4e",
  "pdg_index": 0,
  "replicate": 15,
  "cpd_seed": 15200045,
  "graph": {
    "variables": [
      {
        "name": "A",
        "domain": [
          "a0",
          "a1",
          "a2"
        ]
      },
      {
        "name": "B",
        "domain": [
          "b0",
          "b1"
        ]
      },
      {
        "name": "C",
        "domain": [
          "c0",
          "c1"
        ]
      },
      {
        "name": "D",
        "domain": [
          "d0",
          "d1",
          "d2"
        ]
      },
      {
        "name": "E",
        "domain": [
          "e0",
          "e1",
          "e2"
        ]
      }
    ],
    "edges": [
      {
        "label": "p1",
        "src": "A",
        "src_atoms": [
          "A"
        ],
        "tgt": "B",
        "tgt_atoms": [
          "B"
        ],
        "alpha": 1.0,
        "beta": 1.0
      },
      {
        "label": "p2",
        "src": "B",
        "src_atoms": [
          "B"
        ],
        "tgt": "C",
        "tgt_atoms": [
          "C"
        ],
        "alpha": 1.0,
        "beta": 1.0
      },
      {
        "label": "p3",
        "src": "C",
        "src_atoms": [
          "C"
        ],
        "tgt": "B",
        "tgt_atoms": [
          "B"
        ],
        "alpha": 1.0,
        "beta": 1.0
      },
      {
        "label": "p4",
        "src": "D",
        "src_atoms": [
          "D"
        ],
        "tgt": "C",
        "tgt_atoms": [
          "C"
        ],
        "alpha": 1.0,
        "beta": 1.0
      }
    ]
  },
  "cpds": [
    {
      "label": "p1",
      "src": "A",
      "tgt": "B",
      "shape": [
        3,
        2
      ],
      "values": [
        [
          0.5966191566116622,
          0.4033808433883377
        ],
        [
          0.22342693990777865,
          0.7765730600922214
        ],
        [
          0.5389903655255388,
          0.4610096344744612
        ]
      ]
    },
    {
      "label": "p2",
      "src": "B",
      "tgt": "C",
      "shape": [
        2,
        2
      ],
      "values": [
        [
          0.5068374600231199,
          0.49316253997688003
        ],
        [
          0.5500425169679654,
          0.4499574830320347
        ]
      ]
    },
    {
      "label": "p3",
      "src": "C",
      "tgt": "B",
      "shape": [
        2,
        2
      ],
      "values": [
        [
          0.6527664420668778,
          0.3472335579331221
        ],
        [
          0.8079036834447778,
          0.19209631655522222
        ]
      ]
    },
    {
      "label": "p4",
      "src": "D",
      "tgt": "C",
      "shape": [
        3,
        2
      ],
      "values": [
        [
          0.4800931756084333,
          0.5199068243915668
        ],
        [
          0.7025782178248461,
          0.2974217821751539
        ],
        [
          0.11457909182663438,
          0.8854209081733656
        ]
      ]
    }
  ],
  "strategy_results": {
    "uniform": {
      "pdg_name": "chain_5v_4e",
      "strategy": "uniform",
      "replicate": 15,
      "initial": 0.05010594055056572,
      "final": 7.870567969803233e-06,
      "resolution_pct": 99.98429214603433,
      "distortion_tv": 0.4119684949741194,
      "tv_theta_trace": [
        0.0,
        0.1851809138674127,
        0.3325222778711362,
        0.4933610085842063,
        0.5942481250023662,
        0.6502363797786531,
        0.7085273684434847,
        0.7872365005878805,
        0.8912836764449311,
        0.9588822487617673,
        0.995655731610958,
        1.0088773872993841,
        1.000077612145351,
        1.0116267926448328,
        1.0072796204395946,
        0.9821969300290001,
        0.9937220380614087,
        1.0211657482448477,
        1.0653114830402153,
        1.064516404122938,
        1.0938362027593802
      ],
      "success": true
    },
    "partial": {
      "pdg_name": "chain_5v_4e",
      "strategy": "partial",
      "replicate": 15,
      "initial": 0.05010594055056572,
      "final": 0.00012287026038393378,
      "resolution_pct": 99.75477905606834,
      "distortion_tv": 0.2994672094452372,
      "tv_theta_trace": [
        0.0,
        0.062240227678513414,
        0.10611868243585582,
        0.18322073076090833,
        0.22630288768343526,
        0.20922564109862107,
        0.3098203180288696,
        0.3089899109674255,
        0.3212385074323314,
        0.2799693520173318,
        0.2711089182299024,
        0.34745709460661883,
        0.3449360700861708,
        0.3450382725304998,
        0.3579093854502785,
        0.40385234249699853,
        0.4121592785363815,
        0.4199154203334575,
        0.43241623458643896,
        0.4439100887118226,
        0.4647649201519155
      ],
      "success": true
    },
    "hub": {
      "pdg_name": "chain_5v_4e",
      "strategy": "hub",
      "replicate": 15,
      "initial": 0.05010594055056572,
      "final": 1.070095913746627e-05,
      "resolution_pct": 99.9786433324674,
      "distortion_tv": 0.2777222007059047,
      "tv_theta_trace": [
        0.0,
        0.17954908847134166,
        0.34781779195281964,
        0.49492243126793034,
        0.6023142926177738,
        0.5879228640930814,
        0.6823069661931098,
        0.6993325929931302,
        0.7168702052143793,
        0.7158749539215858,
        0.7417060966615762,
        0.7869667539503947,
        0.8219563492866084,
        0.8148489662272321,
        0.8340529370792442,
        0.834085156982968,
        0.8787702351688038,
        0.8857384581376001,
        0.8939717644045335,
        0.9142562721435137,
        0.9168795891142343
      ],
      "success": true
    }
  }
}