{
  "complete": true,
  "pdg_name": "chain_4v_3e",
  "pdg_index": 0,
  "replicate": 9,
  "cpd_seed": 9200027,
  "graph": {
    "variables": [
      {
        "name": "A",
        "domain": [
          "a0",
          "a1"
        ]
      },
      {
        "name": "B",
        "domain": [
          "b0",
          "b1"
        ]
      },
      {
        "name": "C",
        "domain": [
          "c0",
          "c1"
        ]
      },
      {
        "name": "D",
        "domain": [
          "d0",
          "d1",
          "d2"
        ]
      }
    ],
    "edges": [
      {
        "label": "p1",
        "src": "A",
        "src_atoms": [
          "A"
        ],
        "tgt": "B",
        "tgt_atoms": [
          "B"
        ],
        "alpha": 1.0,
        "beta": 1.0
      },
      {
        "label": "p2",
        "src": "B",
        "src_atoms": [
          "B"
        ],
        "tgt": "C",
        "tgt_atoms": [
          "C"
        ],
        "alpha": 1.0,
        "beta": 1.0
      },
      {
        "label": "p3",
        "src": "C",
        "src_atoms": [
          "C"
        ],
        "tgt": "B",
        "tgt_atoms": [
          "B"
        ],
        "alpha": 1.0,
        "beta": 1.0
      }
    ]
  },
  "cpds": [
    {
      "label": "p1",
      "src": "A",
      "tgt": "B",
      "shape": [
        2,
        2
      ],
      "values": [
        [
          0.4237819516730211,
          0.5762180483269788
        ],
        [
          0.7961486994465732,
          0.20385130055342676
        ]
      ]
    },
    {
      "label": "p2",
      "src": "B",
      "tgt": "C",
      "shape": [
        2,
        2
      ],
      "values": [
        [
          0.4811620994229094,
          0.5188379005770907
        ],
        [
          0.3144818090232343,
          0.6855181909767658
        ]
      ]
    },
    {
      "label": "p3",
      "src": "C",
      "tgt": "B",
      "shape": [
        2,
        2
      ],
      "values": [
        [
          0.39701307269429076,
          0.6029869273057091
        ],
        [
          0.45056156947205084,
          0.5494384305279492
        ]
      ]
    }
  ],
  "strategy_results": {
    "uniform": {
      "pdg_name": "chain_4v_3e",
      "strategy": "uniform",
      "replicate": 9,
      "initial": 0.05369843170046806,
      "final": 2.721745659073349e-06,
      "resolution_pct": 99.99493142430256,
      "distortion_tv": 0.19929542309087905,
      "tv_theta_trace": [
        0.0,
        0.10385285973626265,
        0.21994131952253418,
        0.30567300230404437,
        0.2971946007316483,
        0.2995414276546011,
        0.31201407336529186,
        0.32582753711520573,
        0.33007518881521336,
        0.34551912983420663,
        0.36481005842395964,
        0.36527941498859995,
        0.3781635012873233,
        0.3816349828340896,
        0.38900372358505264,
        0.39249180002883144,
        0.40503704007686103,
        0.4004510859018328,
        0.40732470321753067,
        0.40541381196811044,
        0.41337625272078377
      ],
      "success": true
    },
    "partial": {
      "pdg_name": "chain_4v_3e",
      "strategy": "partial",
      "replicate": 9,
      "initial": 0.05369843170046806,
      "final": 0.01193543616682291,
      "resolution_pct": 77.77321275712626,
      "distortion_tv": 0.17938095286969147,
      "tv_theta_trace": [
        0.0,
        0.015198990832374082,
        0.03496320803422778,
        0.04815098008950716,
        0.04267807910869076,
        0.05632727235065049,
        0.04992678829991826,
        0.069642217940808,
        0.08688453020619832,
        0.07788998071379594,
        0.07773693633049697,
        0.08390628975563072,
        0.09108307265013844,
        0.08603473204286868,
        0.08761110346525706,
        0.09789707562785566,
        0.09235667536214659,
        0.09022041054870047,
        0.10964219687227852,
        0.12746993147831998,
        0.12860728300490948
      ],
      "success": true
    },
    "hub": {
      "pdg_name": "chain_4v_3e",
      "strategy": "hub",
      "replicate": 9,
      "initial": 0.05369843170046806,
      "final": 3.756756541406503e-06,
      "resolution_pct": 99.99300397344496,
      "distortion_tv": 0.24085307771704625,
      "tv_theta_trace": [
        0.0,
        0.10754326988135092,
        0.2183300406174236,
        0.29909365470681026,
        0.2803074773984749,
        0.2784113537296855,
        0.2859314632023937,
        0.28055551096841885,
        0.28404053869717993,
        0.2813495288098581,
        0.290777235029941,
        0.2892577896106098,
        0.2888031549125741,
        0.2763276923797949,
        0.27830692404282464,
        0.2683346150271402,
        0.26592072091922536,
        0.2691571643613837,
        0.27010293734848134,
        0.27723592095879723,
        0.26759843466303035
      ],
      "success": true
    }
  }
}